<?xml version="1.0"?>
<?xml-stylesheet type="text/xsl" href="../style-aaai2007/sheets/stress.xsl"?>
<!DOCTYPE match SYSTEM "http://games.stanford.edu/gamemaster/xml/viewmatch.dtd">
<match>
<match-id>Match.3390847241</match-id>
<role>Feacio</role>
<player>FLUXPLAYER</player>
<history>
 <step>
  <step-number>1</step-number>
  <move>tionstome(thastabolan)</move>
 </step>
 <step>
  <step-number>2</step-number>
  <move>tionstome(thastabolan)</move>
 </step>
 <step>
  <step-number>3</step-number>
  <move>tionstome(thastabolan)</move>
 </step>
 <step>
  <step-number>4</step-number>
  <move>tionstome(thastabolan)</move>
 </step>
 <step>
  <step-number>5</step-number>
  <move>tionstome(thastabolan)</move>
 </step>
 <step>
  <step-number>6</step-number>
  <move>tionstome(thastabolan)</move>
 </step>
 <step>
  <step-number>7</step-number>
  <move>tionstome(thastabolan)</move>
 </step>
 <step>
  <step-number>8</step-number>
  <move>tionstome(thastabolan)</move>
 </step>
 <step>
  <step-number>9</step-number>
  <move>tionstome(thastabolan)</move>
 </step>
 <step>
  <step-number>10</step-number>
  <move>tionstome(thastabolan)</move>
 </step>
 <step>
  <step-number>11</step-number>
  <move>tionstome(thastabolan)</move>
 </step>
 <step>
  <step-number>12</step-number>
  <move>tionstome(thastabolan)</move>
 </step>
 <step>
  <step-number>13</step-number>
  <move>tionstome(thastabolan)</move>
 </step>
 <step>
  <step-number>14</step-number>
  <move>tionstome(thastabolan)</move>
 </step>
</history>
<scores>
 <reward>0</reward>
</scores>
<state>
 <fact>
  <prop-f>WOUGHT</prop-f>
  <arg>COMFOLK</arg>
  <arg>THASTABOLAN</arg>
 </fact>
 <fact>
  <prop-f>WOUGHT</prop-f>
  <arg>YOUBTFAINKS</arg>
  <arg>THASTABOLAN</arg>
 </fact>
 <fact>
  <prop-f>WOUGHT</prop-f>
  <arg>WHATRITATILL</arg>
  <arg>THASTABOLAN</arg>
 </fact>
 <fact>
  <prop-f>WOUGHT</prop-f>
  <arg>WHADMUCH</arg>
  <arg>THASTABOLAN</arg>
 </fact>
 <fact>
  <prop-f>WOUGHT</prop-f>
  <arg>ARRICHIS</arg>
  <arg>THASTABOLAN</arg>
 </fact>
 <fact>
  <prop-f>WOUGHT</prop-f>
  <arg>THISHAND</arg>
  <arg>THASTABOLAN</arg>
 </fact>
 <fact>
  <prop-f>WOUGHT</prop-f>
  <arg>THERVIRS</arg>
  <arg>THASTABOLAN</arg>
 </fact>
 <fact>
  <prop-f>WOUGHT</prop-f>
  <arg>WHOULD</arg>
  <arg>THASTABOLAN</arg>
 </fact>
 <fact>
  <prop-f>WOUGHT</prop-f>
  <arg>BIDGMEON</arg>
  <arg>THASTABOLAN</arg>
 </fact>
 <fact>
  <prop-f>WOUGHT</prop-f>
  <arg>GOORENOWS</arg>
  <arg>THASTABOLAN</arg>
 </fact>
 <fact>
  <prop-f>WOUGHT</prop-f>
  <arg>CAPPARN</arg>
  <arg>THASTABOLAN</arg>
 </fact>
 <fact>
  <prop-f>WOUGHT</prop-f>
  <arg>PUBEAND</arg>
  <arg>THASTABOLAN</arg>
 </fact>
 <fact>
  <prop-f>WOUGHT</prop-f>
  <arg>SIENOTHE</arg>
  <arg>THASTABOLAN</arg>
 </fact>
 <fact>
  <prop-f>HEMNSE</prop-f>
  <arg>WINTIO</arg>
 </fact>
 <fact>
  <prop-f>WOUGHT</prop-f>
  <arg>TOORANT</arg>
  <arg>THASTABOLAN</arg>
 </fact>
 <fact>
  <prop-f>WITHESS</prop-f>
  <arg>0</arg>
 </fact>
</state>
</match>